segmentUSD/__init__.py
segmentUSD/ultrasound.py
segmentUSD-0.1.1.dist-info/METADATA
segmentUSD-0.1.1.dist-info/WHEEL
segmentUSD-0.1.1.dist-info/top_level.txt
segmentUSD-0.1.1.dist-info/RECORD
